MANIFEST.in
requirements.txt
setup.cfg
setup.py
napalm_ios/__init__.py
napalm_ios/ios.py
napalm_ios.egg-info/PKG-INFO
napalm_ios.egg-info/SOURCES.txt
napalm_ios.egg-info/dependency_links.txt
napalm_ios.egg-info/requires.txt
napalm_ios.egg-info/top_level.txt
napalm_ios/templates/delete_ntp_peers.j2
napalm_ios/templates/delete_ntp_servers.j2
napalm_ios/templates/delete_snmp_config.j2
napalm_ios/templates/set_hostname.j2
napalm_ios/templates/set_ntp_peers.j2
napalm_ios/templates/set_ntp_servers.j2
napalm_ios/templates/snmp_config.j2